nilm_metadata/__init__.py
nilm_metadata/central_metadata/__init__.py
nilm_metadata/central_metadata/appliance_types/__init__.py
nilm_metadata/central_metadata/appliance_types/appliance.yaml
nilm_metadata/central_metadata/appliance_types/cold.yaml
nilm_metadata/central_metadata/appliance_types/commercial.yaml
nilm_metadata/central_metadata/appliance_types/components.yaml
nilm_metadata/central_metadata/appliance_types/consumer_electronics.yaml
nilm_metadata/central_metadata/appliance_types/cooking.yaml
nilm_metadata/central_metadata/appliance_types/heating.yaml
nilm_metadata/central_metadata/appliance_types/ict.yaml
nilm_metadata/central_metadata/appliance_types/lighting.yaml
nilm_metadata/central_metadata/appliance_types/misc.yaml
nilm_metadata/central_metadata/appliance_types/wet.yaml
nilm_metadata/central_metadata/country.yaml
nilm_metadata/convert_yaml_to_hdf5.py
nilm_metadata/file_management.py
nilm_metadata/object_concatenation.py
nilm_metadata/tests/__init__.py
nilm_metadata/tests/test_convert_yaml_to_hdf5.py
nilm_metadata/tests/test_nilm_metadata.py
nilm_metadata/tests/test_object_concatenation.py
nilm_metadata/version.py
nilm_metadata_s14pe-0.2.5.dev5.dist-info/LICENSE
nilm_metadata_s14pe-0.2.5.dev5.dist-info/METADATA
nilm_metadata_s14pe-0.2.5.dev5.dist-info/WHEEL
nilm_metadata_s14pe-0.2.5.dev5.dist-info/RECORD
