Metadata-Version: 2.1
Name: nilm-metadata-s14pe
Version: 0.2.5.dev5
Summary: Concatenate NILM metadata with updated dependencies
Author: FelixS
Author-email: felix.sievers@baind.de
Requires-Python: >=3.11,<4.0
Classifier: Programming Language :: Python :: 3
Classifier: Programming Language :: Python :: 3.11
Classifier: Programming Language :: Python :: 3.12
Requires-Dist: pandas (>=2.2.3,<3.0.0)
Requires-Dist: pyyaml (>=6.0.2,<7.0.0)
Requires-Dist: six (>=1.16.0,<2.0.0)
